{
  "__comment": "Designed_by_Snhnry_-_www.tlaminecraft.com",
  "textures": {
    "particle": "block/iron_block",
    "iron_block": "block/acacia_log",
    "texture": "block/sand_fence"
  },
  "elements": [
    {
      "__comment": "Center_post",
      "from": [
        7,
        0,
        7
      ],
      "to": [
        9,
        16,
        9
      ],
      "faces": {
        "down": {
          "uv": [
            0,
            0,
            16,
            16
          ],
          "texture": "#iron_block",
          "cullface": "down"
        },
        "up": {
          "uv": [
            0,
            0,
            16,
            16
          ],
          "texture": "#iron_block",
          "cullface": "up"
        },
        "north": {
          "uv": [
            5.5,
            0,
            10.5,
            16
          ],
          "texture": "#iron_block"
        },
        "south": {
          "uv": [
            5.5,
            0,
            10.5,
            16
          ],
          "texture": "#iron_block"
        },
        "west": {
          "uv": [
            5,
            0,
            12.5,
            16
          ],
          "texture": "#iron_block"
        },
        "east": {
          "uv": [
            5,
            0,
            12.5,
            16
          ],
          "texture": "#iron_block"
        }
      }
    },
    {
      "from": [
        8,
        0,
        0
      ],
      "to": [
        8.0625,
        16,
        7
      ],
      "faces": {
        "west": {
          "uv": [
            0,
            0,
            8,
            16
          ],
          "texture": "#texture"
        },
        "east": {
          "uv": [
            8,
            0,
            0,
            16
          ],
          "texture": "#texture"
        }
      }
    },
    {
      "from": [
        7.0625,
        16,
        7.0625
      ],
      "to": [
        8.9375,
        16.625,
        8.9375
      ],
      "faces": {
        "up": {
          "uv": [
            0,
            0,
            9,
            9
          ],
          "texture": "#iron_block",
          "cullface": "up"
        },
        "north": {
          "uv": [
            7.0625,
            0,
            8.9375,
            0
          ],
          "texture": "#iron_block",
          "cullface": "up"
        },
        "south": {
          "uv": [
            7.0625,
            0,
            8.9375,
            0
          ],
          "texture": "#iron_block",
          "cullface": "up"
        },
        "west": {
          "uv": [
            7.0625,
            0,
            8.9375,
            0
          ],
          "texture": "#iron_block",
          "cullface": "up"
        },
        "east": {
          "uv": [
            7.0625,
            0,
            8.9375,
            0
          ],
          "texture": "#iron_block",
          "cullface": "up"
        }
      }
    },
    {
      "from": [
        9,
        0,
        8
      ],
      "to": [
        16,
        16,
        8.0625
      ],
      "faces": {
        "north": {
          "uv": [
            0,
            0,
            8,
            16
          ],
          "texture": "#texture"
        },
        "south": {
          "uv": [
            8,
            0,
            0,
            16
          ],
          "texture": "#texture"
        }
      }
    },
    {
      "from": [
        8,
        0,
        9
      ],
      "to": [
        8.0625,
        16,
        16
      ],
      "faces": {
        "west": {
          "uv": [
            8,
            0,
            0,
            16
          ],
          "texture": "#texture"
        },
        "east": {
          "uv": [
            0,
            0,
            8,
            16
          ],
          "texture": "#texture"
        }
      }
    }
  ]
}
